COPYING
MANIFEST.in
NOTES
PROTOCOL.md
README.md
setup.py
sshed/__init__.py
sshed/edssh.py
sshed/packethandler.py
sshed/sshed.py
sshed/sshed_client.py
sshedit.egg-info/PKG-INFO
sshedit.egg-info/SOURCES.txt
sshedit.egg-info/dependency_links.txt
sshedit.egg-info/entry_points.txt
sshedit.egg-info/top_level.txt